sn_nacl-0.4.dist-info/top_level.txt
sn_nacl-0.4.dist-info/RECORD
sn_nacl-0.4.dist-info/WHEEL
sn_nacl-0.4.dist-info/METADATA
nacl/data_cuts.py
nacl/minimizers.py
nacl/minimize.py
nacl/handles.py
nacl/distance.py
nacl/dataset.py
nacl/__init__.py
nacl/fit.py
nacl/instruments.py
nacl/simulations/etc.py
nacl/simulations/randutils.py
nacl/simulations/reindex.py
nacl/simulations/flux_simulator.py
nacl/simulations/__init__.py
nacl/simulations/jla.py
nacl/simulations/ideal.py
nacl/simulations/k21.py
nacl/models/variancemodels.py
nacl/models/salt.py
nacl/models/constraints.py
nacl/models/regularizations.py
nacl/lib/indextools.py
nacl/lib/atmosphericmodel.py
nacl/lib/spectrum.py
nacl/lib/fitparameters.py
nacl/lib/interpolation.py
nacl/lib/dataproxy.py
nacl/lib/stellarlibs.py
nacl/lib/bspline.py
nacl/lib/_libnacl.cpython-310-x86_64-linux-gnu.so
nacl/lib/optim.py
nacl/lib/__init__.py
nacl/lib/constants.py
nacl/lib/instruments.py
nacl/lib/robuststat.py
nacl/plotting/plots.py
nacl/plotting/plottools.py
nacl/plotting/__init__.py
nacl/util/io.py
nacl/util/saltpath.py
nacl/util/salt2.py
